hiproc/EDR_Stats.py
hiproc/FlatFile.py
hiproc/HiBeautify.py
hiproc/HiCal.py
hiproc/HiColorInit.py
hiproc/HiColorNorm.py
hiproc/HiJACK.py
hiproc/HiJitReg.py
hiproc/HiNoProj.py
hiproc/HiPrecisionInit.py
hiproc/HiSlither.py
hiproc/HiStitch.py
hiproc/HiccdStitch.py
hiproc/JitPlot.py
hiproc/SlitherStats.py
hiproc/__init__.py
hiproc/bfeval.py
hiproc/bitflips.py
hiproc/bitunflip.py
hiproc/bobclean.py
hiproc/fft_clean.py
hiproc/hiproc.py
hiproc/hirise.py
hiproc/img.py
hiproc/lisfix.py
hiproc/mdr2cub.py
hiproc/resolve_jitter.py
hiproc/rjdiff.py
hiproc/rjdiffsmear.py
hiproc/rjplot.py
hiproc/util.py
hiproc/data/EDR_Stats_gains_config.pvl
hiproc/data/HiBeautify.conf
hiproc/data/HiCal.conf
hiproc/data/HiColorNorm.conf
hiproc/data/HiGainFx.conf
hiproc/data/HiJACK.conf
hiproc/data/HiJitReg.conf
hiproc/data/HiNoProj.conf
hiproc/data/HiPrecisionInit.conf
hiproc/data/HiRISE_Gain_Drift_Correction_Bin1.0001.csv
hiproc/data/HiRISE_Gain_Drift_Correction_Bin2.0001.csv
hiproc/data/HiRISE_Gain_Drift_Correction_Bin4.0001.csv
hiproc/data/HiStitch.conf
hiproc/data/HiccdStitch.conf
hiproc/data/NoiseFilter.conf
hiproc/data/ResolveJitter.conf
hiproc/data/experimental-HiCal.conf
hiproc/data/experimental-hical.noise.pipelines.conf
hiproc/data/hical.noise.pipelines.conf
hiproc/data/hical.pipelines.conf
hiproc-0.11.0.dist-info/AUTHORS.rst
hiproc-0.11.0.dist-info/LICENSE
hiproc-0.11.0.dist-info/METADATA
hiproc-0.11.0.dist-info/WHEEL
hiproc-0.11.0.dist-info/entry_points.txt
hiproc-0.11.0.dist-info/top_level.txt
hiproc-0.11.0.dist-info/RECORD
