Metadata-Version: 2.1
Name: hiproc
Version: 0.11.0
Summary: A library to help process HiRISE EDRs with ISIS.
Home-page: https://github.com/rbeyer/hiproc
Author: attr:hiproc.__version__
Author-email: rbeyer@seti.org
License: UNKNOWN
Keywords: HiRISE
Platform: UNKNOWN
Classifier: Programming Language :: Python :: 3.6
Classifier: Programming Language :: Python :: 3.7
Classifier: Programming Language :: Python :: 3.8
Classifier: License :: OSI Approved :: Apache Software License
Classifier: Operating System :: OS Independent
Classifier: Development Status :: 2 - Pre-Alpha
Classifier: Natural Language :: English
Requires-Python: >=3.6
Requires-Dist: gdal (>=3.0.1)
Requires-Dist: kalasiris (>=1.8.0)
Requires-Dist: matplotlib (>=3.2.1)
Requires-Dist: multidict
Requires-Dist: numpy (>=1.18.1)
Requires-Dist: pvl (>=1.0.1)
Requires-Dist: scipy (>=1.4.1)
